text_converter.py
text_converter_yes-1.0.0.dist-info/METADATA
text_converter_yes-1.0.0.dist-info/WHEEL
text_converter_yes-1.0.0.dist-info/top_level.txt
text_converter_yes-1.0.0.dist-info/RECORD
