Metadata-Version: 2.1
Name: text-converter-yes
Version: 1.0.0
Summary: A Python library for converting text to uppercase.
Home-page: https://github.com/yourusername/text_converter
Author: __token__
Author-email: your.email@example.com
License: UNKNOWN
Platform: UNKNOWN
Classifier: Programming Language :: Python :: 3
Classifier: License :: OSI Approved :: MIT License
Classifier: Operating System :: OS Independent
